pypi_express_pub/__init__.py
pypi_express_pub/publish.py
pypi_express_pub-0.0.5.dist-info/METADATA
pypi_express_pub-0.0.5.dist-info/WHEEL
pypi_express_pub-0.0.5.dist-info/entry_points.txt
pypi_express_pub-0.0.5.dist-info/top_level.txt
pypi_express_pub-0.0.5.dist-info/RECORD
